README.md
setup.cfg
setup.py
beholder/__init__.py
beholder/argparser.py
beholder/cfg_reader.py
beholder/cfg_validator.py
beholder/const.py
beholder/errors.py
beholder/fetcher.py
beholder/main.py
beholder/opts_validator.py
beholder/analyzer/file_manager.py
beholder/analyzer/state_checker.py
beholder/file_comparator/__init__.py
beholder/file_comparator/comparators.py
beholder/reports/__init__.py
beholder/reports/report_builder.py
beholder/reports/reporter_factory.py
beholder/reports/reporters.py
beholderteam_beholder.egg-info/PKG-INFO
beholderteam_beholder.egg-info/SOURCES.txt
beholderteam_beholder.egg-info/dependency_links.txt
beholderteam_beholder.egg-info/requires.txt
beholderteam_beholder.egg-info/top_level.txt