Metadata-Version: 2.1
Name: beholderteam-beholder
Version: 0.1.0
Summary: A simple tool to monitor selected websites
Home-page: UNKNOWN
Author: beholder-devteam
Maintainer: beholder_devteam
License: UNKNOWN
Platform: UNKNOWN
Requires-Python: >=3.8.0
Provides-Extra: dev
